create_agentic_rag/__init__.py
create_agentic_rag/cli.py
create_agentic_rag/template/.env.example
create_agentic_rag/template/.gitignore
create_agentic_rag/template/README.md
create_agentic_rag/template/requirements.txt
create_agentic_rag/template/app/config.py
create_agentic_rag/template/app/main.py
create_agentic_rag/template/app/api/dependencies.py
create_agentic_rag/template/app/api/endpoints.py
create_agentic_rag/template/app/api/models.py
create_agentic_rag/template/app/core/llm.py
create_agentic_rag/template/app/rag/graph.py
create_agentic_rag/template/app/rag/models.py
create_agentic_rag/template/app/rag/nodes.py
create_agentic_rag/template/app/rag/tools.py
create_agentic_rag/template/app/services/chat_service.py
create_agentic_rag/template/app/utils/helpers.py
create_agentic_rag/template/app/utils/logging.py
create_agentic_rag/template/app/utils/prompts.py
create_agentic_rag-0.1.2.dist-info/METADATA
create_agentic_rag-0.1.2.dist-info/WHEEL
create_agentic_rag-0.1.2.dist-info/entry_points.txt
create_agentic_rag-0.1.2.dist-info/top_level.txt
create_agentic_rag-0.1.2.dist-info/RECORD
