Metadata-Version: 2.4
Name: create-agentic-rag
Version: 0.1.2
Summary: A boilerplate for creating agentic RAG applications
Author: 
License-Expression: MIT
Classifier: Programming Language :: Python :: 3
Classifier: Operating System :: OS Independent
Requires-Python: >=3.8
Requires-Dist: click>=8.0.0
Requires-Dist: rich>=10.0.0
